repartipy/__init__.py
repartipy/exceptions/__init__.py
repartipy/exceptions/exceptions.py
repartipy/size_estimator.py
repartipy-0.1.7.dist-info/LICENSE
repartipy-0.1.7.dist-info/METADATA
repartipy-0.1.7.dist-info/WHEEL
repartipy-0.1.7.dist-info/RECORD
