Metadata-Version: 2.1
Name: repartipy
Version: 0.1.7
Summary: Helper for handling PySpark DataFrame partition size 📑🎛️
Home-page: https://github.com/sakjung/repartipy
License: Apache-2.0
Keywords: apachespark,spark,pyspark
Author: sakjung
Author-email: ssangyu123@gmail.com
Requires-Python: >=3.7
Classifier: License :: OSI Approved :: Apache Software License
Classifier: Programming Language :: Python :: 3
Classifier: Programming Language :: Python :: 3.7
Classifier: Programming Language :: Python :: 3.8
Classifier: Programming Language :: Python :: 3.9
Classifier: Programming Language :: Python :: 3.10
Classifier: Programming Language :: Python :: 3.11
Classifier: Programming Language :: Python :: 3.12
Requires-Dist: packaging (>=23,<24)
Requires-Dist: typing-extensions (>=4.5,<5.0)
